get_ipinfo.py
get_ipinfo-0.1.1.dist-info/LICENSE.txt
get_ipinfo-0.1.1.dist-info/METADATA
get_ipinfo-0.1.1.dist-info/WHEEL
get_ipinfo-0.1.1.dist-info/top_level.txt
get_ipinfo-0.1.1.dist-info/RECORD
