Metadata-Version: 2.1
Name: get-ipinfo
Version: 0.1.1
Summary: Get Country, Region, City, GPS ,ZIP and ISP
Home-page: UNKNOWN
Author: Muhammad Sohaib
Author-email: sohaib.cs1@gmail.com
License: UNKNOWN
Keywords: ip,address,location
Platform: UNKNOWN
Classifier: Intended Audience :: Developers
Classifier: Programming Language :: Python :: 3
Classifier: License :: OSI Approved :: MIT License
Classifier: Operating System :: OS Independent
Requires-Python: >=3.6
License-File: LICENSE.txt
